{
  "reading": {
    "title": "Reading",
    "type": "page"
  },
  "learning": {
    "title": "Learning",
    "type": "menu",
    "items": {
      "Z-TODO": {
        "title": "Z Todo",
        "href": "/Z-TODO"
      },
      "about_imgs": {
        "title": "About Imgs",
        "href": "/about_imgs"
      },
      "base64_intro": {
        "title": "Base64 Intro",
        "href": "/base64_intro"
      },
      "bitwise": {
        "title": "Bitwise",
        "href": "/bitwise"
      },
      "regex": {
        "title": "Regex",
        "href": "/regex"
      },
      "unix_philosophy": {
        "title": "Unix Philosophy",
        "href": "/unix_philosophy"
      },
      "vim_note": {
        "title": "Vim Note",
        "href": "/vim_note"
      },
      "functional_programming": {
        "title": "Functional Programming",
        "href": "/functional_programmingtemp/02learning_notes/functional_programming/monad"
      },
      "docker": {
        "title": "Docker",
        "href": "/dockertemp/02learning_notes/docker/docker_run_connect"
      },
      "design": {
        "title": "Design",
        "href": "/designtemp/02learning_notes/design/learn_figma"
      },
      "IDL": {
        "title": "Idl",
        "href": "/IDLtemp/02learning_notes/IDL/intro"
      },
      "sql": {
        "title": "SQL",
        "href": "/sqltemp/02learning_notes/sql/learn_sql"
      },
      "redis": {
        "title": "Redis",
        "href": "/redistemp/02learning_notes/redis/intro"
      },
      "git": {
        "title": "Git",
        "href": "/gittemp/02learning_notes/git/intro"
      },
      "golang": {
        "title": "Golang",
        "href": "/golangtemp/02learning_notes/golang/go_stuff"
      },
      "rust": {
        "title": "Rust",
        "href": "/rusttemp/02learning_notes/rust/begin"
      },
      "cpp": {
        "title": "Cpp",
        "href": "/cpptemp/02learning_notes/cpp/cmake_intro"
      },
      "shell": {
        "title": "Shell",
        "href": "/shelltemp/02learning_notes/shell/commands"
      },
      "markup": {
        "title": "Markup",
        "href": "/markuptemp/02learning_notes/markup/learn_markdown"
      },
      "ml": {
        "title": "Ml",
        "href": "/mltemp/02learning_notes/ml/Mahalanobias_distance"
      },
      "haskell": {
        "title": "Haskell",
        "href": "/haskelltemp/02learning_notes/haskell/README"
      },
      "blockchain": {
        "title": "Blockchain",
        "href": "/blockchaintemp/02learning_notes/blockchain/blockstack"
      },
      "openGL": {
        "title": "Opengl",
        "href": "/openGLtemp/02learning_notes/openGL/glsl/glsl_intro"
      },
      "data_structure_&_algorithm": {
        "title": "Data Structure & Algorithm",
        "href": "/data_structure_&_algorithmtemp/02learning_notes/data_structure_&_algorithm/Tree and forest"
      },
      "linux": {
        "title": "Linux",
        "href": "/linuxtemp/02learning_notes/linux/linux_c_archived"
      },
      "python": {
        "title": "Python",
        "href": "/pythontemp/02learning_notes/python/env_config"
      },
      "computer_graphics": {
        "title": "Computer Graphics",
        "href": "/computer_graphicstemp/02learning_notes/computer_graphics/computer_graphics_from_scratch/reading_note"
      },
      "front_end_notes": {
        "title": "Front End Notes",
        "href": "/front_end_notestemp/02learning_notes/front_end_notes/browser/apis"
      }
    }
  },
  "Z-TODO": {
    "title": "Z Todo",
    "display": "hidden",
    "type": "page",
    "theme": {
      "toc": true,
      "breadcrumb": false
    }
  },
  "about_imgs": {
    "title": "About Imgs",
    "display": "hidden",
    "type": "page",
    "theme": {
      "toc": true,
      "breadcrumb": false
    }
  },
  "base64_intro": {
    "title": "Base64 Intro",
    "display": "hidden",
    "type": "page",
    "theme": {
      "toc": true,
      "breadcrumb": false
    }
  },
  "bitwise": {
    "title": "Bitwise",
    "display": "hidden",
    "type": "page",
    "theme": {
      "toc": true,
      "breadcrumb": false
    }
  },
  "regex": {
    "title": "Regex",
    "display": "hidden",
    "type": "page",
    "theme": {
      "toc": true,
      "breadcrumb": false
    }
  },
  "unix_philosophy": {
    "title": "Unix Philosophy",
    "display": "hidden",
    "type": "page",
    "theme": {
      "toc": true,
      "breadcrumb": false
    }
  },
  "vim_note": {
    "title": "Vim Note",
    "display": "hidden",
    "type": "page",
    "theme": {
      "toc": true,
      "breadcrumb": false
    }
  },
  "functional_programming": {
    "title": "Functional Programming",
    "display": "hidden",
    "type": "page",
    "theme": {
      "toc": true,
      "breadcrumb": false
    }
  },
  "docker": {
    "title": "Docker",
    "display": "hidden",
    "type": "page",
    "theme": {
      "toc": true,
      "breadcrumb": false
    }
  },
  "design": {
    "title": "Design",
    "display": "hidden",
    "type": "page",
    "theme": {
      "toc": true,
      "breadcrumb": false
    }
  },
  "IDL": {
    "title": "Idl",
    "display": "hidden",
    "type": "page",
    "theme": {
      "toc": true,
      "breadcrumb": false
    }
  },
  "sql": {
    "title": "SQL",
    "display": "hidden",
    "type": "page",
    "theme": {
      "toc": true,
      "breadcrumb": false
    }
  },
  "redis": {
    "title": "Redis",
    "display": "hidden",
    "type": "page",
    "theme": {
      "toc": true,
      "breadcrumb": false
    }
  },
  "git": {
    "title": "Git",
    "display": "hidden",
    "type": "page",
    "theme": {
      "toc": true,
      "breadcrumb": false
    }
  },
  "golang": {
    "title": "Golang",
    "display": "hidden",
    "type": "page",
    "theme": {
      "toc": true,
      "breadcrumb": false
    }
  },
  "rust": {
    "title": "Rust",
    "display": "hidden",
    "type": "page",
    "theme": {
      "toc": true,
      "breadcrumb": false
    }
  },
  "cpp": {
    "title": "Cpp",
    "display": "hidden",
    "type": "page",
    "theme": {
      "toc": true,
      "breadcrumb": false
    }
  },
  "shell": {
    "title": "Shell",
    "display": "hidden",
    "type": "page",
    "theme": {
      "toc": true,
      "breadcrumb": false
    }
  },
  "markup": {
    "title": "Markup",
    "display": "hidden",
    "type": "page",
    "theme": {
      "toc": true,
      "breadcrumb": false
    }
  },
  "ml": {
    "title": "Ml",
    "display": "hidden",
    "type": "page",
    "theme": {
      "toc": true,
      "breadcrumb": false
    }
  },
  "haskell": {
    "title": "Haskell",
    "display": "hidden",
    "type": "page",
    "theme": {
      "toc": true,
      "breadcrumb": false
    }
  },
  "blockchain": {
    "title": "Blockchain",
    "display": "hidden",
    "type": "page",
    "theme": {
      "toc": true,
      "breadcrumb": false
    }
  },
  "openGL": {
    "title": "Opengl",
    "display": "hidden",
    "type": "page",
    "theme": {
      "toc": true,
      "breadcrumb": false
    }
  },
  "data_structure_&_algorithm": {
    "title": "Data Structure & Algorithm",
    "display": "hidden",
    "type": "page",
    "theme": {
      "toc": true,
      "breadcrumb": false
    }
  },
  "linux": {
    "title": "Linux",
    "display": "hidden",
    "type": "page",
    "theme": {
      "toc": true,
      "breadcrumb": false
    }
  },
  "python": {
    "title": "Python",
    "display": "hidden",
    "type": "page",
    "theme": {
      "toc": true,
      "breadcrumb": false
    }
  },
  "computer_graphics": {
    "title": "Computer Graphics",
    "display": "hidden",
    "type": "page",
    "theme": {
      "toc": true,
      "breadcrumb": false
    }
  },
  "front_end_notes": {
    "title": "Front End Notes",
    "display": "hidden",
    "type": "page",
    "theme": {
      "toc": true,
      "breadcrumb": false
    }
  },
  "index": {
    "type": "page",
    "title": "Coyote's Portfolio",
    "display": "hidden",
    "theme": {
      "layout": "raw"
    }
  }
}